{
  "stations": [
    {
      "name": "Бульвар Рокоссовского",
      "line": "Сокольническая линия",
      "date": "10.09.2016",
      "depth": -8.0,
      "hasConnection": true
    },
    {
      "name": "Черкизовская",
      "line": "Сокольническая линия",
      "date": "01.08.1990",
      "depth": -9.0,
      "hasConnection": true
    },
    {
      "name": "Преображенская площадь",
      "line": "Сокольническая линия",
      "date": "31.12.1965",
      "depth": -8.0,
      "hasConnection": false
    },
    {
      "name": "Сокольники",
      "line": "Сокольническая линия",
      "date": "15.05.1935",
      "depth": -9.0,
      "hasConnection": false
    },
    {
      "name": "Красносельская",
      "line": "Сокольническая линия",
      "date": "15.05.1935",
      "depth": -8.0,
      "hasConnection": false
    },
    {
      "name": "Комсомольская",
      "line": "Сокольническая линия",
      "date": "15.05.1935",
      "depth": -8.0,
      "hasConnection": true
    },
    {
      "name": "Красные ворота",
      "line": "Сокольническая линия",
      "date": "15.05.1935",
      "depth": -31.0,
      "hasConnection": false
    },
    {
      "name": "Чистые пруды",
      "line": "Сокольническая линия",
      "date": "15.05.1935",
      "depth": -35.0,
      "hasConnection": true
    },
    {
      "name": "Лубянка",
      "line": "Сокольническая линия",
      "date": "15.05.1935",
      "depth": -32.5,
      "hasConnection": true
    },
    {
      "name": "Охотныи ряд",
      "line": "Сокольническая линия",
      "date": "15.05.1935",
      "depth": -15.0,
      "hasConnection": false
    },
    {
      "name": "Библиотека имени Ленина",
      "line": "Сокольническая линия",
      "date": "15.05.1935",
      "depth": -12.0,
      "hasConnection": true
    },
    {
      "name": "Кропоткинская",
      "line": "Сокольническая линия",
      "date": "15.05.1935",
      "depth": -13.0,
      "hasConnection": false
    },
    {
      "name": "Парк Культуры",
      "line": "Сокольническая линия",
      "date": "01.01.1950",
      "depth": -40.0,
      "hasConnection": true
    },
    {
      "name": "Фрунзенская",
      "line": "Сокольническая линия",
      "date": "01.05.1957",
      "depth": -42.0,
      "hasConnection": false
    },
    {
      "name": "Спортивная",
      "line": "Сокольническая линия",
      "date": "01.05.1957",
      "depth": -42.0,
      "hasConnection": true
    },
    {
      "name": "Воробьевы горы",
      "line": "Сокольническая линия",
      "date": "12.01.1959",
      "depth": 10.0,
      "hasConnection": false
    },
    {
      "name": "Университет",
      "line": "Сокольническая линия",
      "date": "12.01.1959",
      "depth": -26.5,
      "hasConnection": false
    },
    {
      "name": "Проспект Вернадского",
      "line": "Сокольническая линия",
      "date": "07.12.2021",
      "depth": -8.0,
      "hasConnection": false
    },
    {
      "name": "Юго-Западная",
      "line": "Сокольническая линия",
      "date": "30.12.1963",
      "depth": -8.0,
      "hasConnection": false
    },
    {
      "name": "Тропарево",
      "line": "Сокольническая линия",
      "date": "08.12.2014",
      "depth": -12.0,
      "hasConnection": false
    },
    {
      "name": "Румянцево",
      "line": "Сокольническая линия",
      "date": "18.01.2016",
      "depth": -12.0,
      "hasConnection": false
    },
    {
      "name": "Саларьево",
      "line": "Сокольническая линия",
      "date": "15.02.2016",
      "depth": -12.0,
      "hasConnection": false
    },
    {
      "name": "Филатов Луг",
      "line": "Сокольническая линия",
      "date": "20.06.2019",
      "depth": 0.0,
      "hasConnection": false
    },
    {
      "name": "Прокшино",
      "line": "Сокольническая линия",
      "date": "20.06.2019",
      "depth": 0.0,
      "hasConnection": false
    },
    {
      "name": "Ольховая",
      "line": "Сокольническая линия",
      "date": "20.06.2019",
      "hasConnection": false
    },
    {
      "name": "Коммунарка",
      "line": "Сокольническая линия",
      "date": "20.06.2019",
      "hasConnection": false
    },
    {
      "name": "Ховрино",
      "line": "Замоскворецкая линия",
      "date": "31.12.2017",
      "depth": -14.0,
      "hasConnection": false
    },
    {
      "name": "Беломорская",
      "line": "Замоскворецкая линия",
      "date": "20.12.2018",
      "depth": -18.0,
      "hasConnection": false
    },
    {
      "name": "Речнои вокзал",
      "line": "Замоскворецкая линия",
      "date": "31.12.1964",
      "depth": -6.0,
      "hasConnection": false
    },
    {
      "name": "Водныи стадион",
      "line": "Замоскворецкая линия",
      "date": "31.12.1964",
      "depth": -6.0,
      "hasConnection": false
    },
    {
      "name": "Воиковская",
      "line": "Замоскворецкая линия",
      "date": "31.12.1964",
      "depth": -7.0,
      "hasConnection": false
    },
    {
      "name": "Сокол",
      "line": "Замоскворецкая линия",
      "date": "11.09.1938",
      "depth": -9.6,
      "hasConnection": false
    },
    {
      "name": "Аэропорт",
      "line": "Замоскворецкая линия",
      "date": "11.09.1938",
      "depth": -10.0,
      "hasConnection": false
    },
    {
      "name": "Динамо",
      "line": "Замоскворецкая линия",
      "date": "11.09.1938",
      "depth": -39.6,
      "hasConnection": true
    },
    {
      "name": "Белорусская",
      "line": "Замоскворецкая линия",
      "date": "11.09.1938",
      "depth": -33.1,
      "hasConnection": true
    },
    {
      "name": "Маяковская",
      "line": "Замоскворецкая линия",
      "date": "11.09.1938",
      "depth": -33.1,
      "hasConnection": false
    },
    {
      "name": "Тверская",
      "line": "Замоскворецкая линия",
      "date": "20.07.1979",
      "depth": -42.0,
      "hasConnection": true
    },
    {
      "name": "Театральная",
      "line": "Замоскворецкая линия",
      "date": "11.09.1938",
      "depth": -33.9,
      "hasConnection": true
    },
    {
      "name": "Новокузнецкая",
      "line": "Замоскворецкая линия",
      "date": "20.11.1943",
      "depth": -37.5,
      "hasConnection": true
    },
    {
      "name": "Павелецкая",
      "line": "Замоскворецкая линия",
      "date": "01.01.1950",
      "depth": -33.5,
      "hasConnection": true
    },
    {
      "name": "Автозаводская",
      "line": "Замоскворецкая линия",
      "date": "10.09.2016",
      "depth": -11.0,
      "hasConnection": true
    },
    {
      "name": "Технопарк",
      "line": "Замоскворецкая линия",
      "date": "28.12.2015",
      "depth": 0.0,
      "hasConnection": false
    },
    {
      "name": "Коломенская",
      "line": "Замоскворецкая линия",
      "date": "11.08.1969",
      "depth": -9.0,
      "hasConnection": false
    },
    {
      "name": "Каширская",
      "line": "Замоскворецкая линия",
      "date": "11.08.1969",
      "depth": -7.0,
      "hasConnection": true
    },
    {
      "name": "Кантемировская",
      "line": "Замоскворецкая линия",
      "date": "30.12.1984",
      "depth": -8.0,
      "hasConnection": false
    },
    {
      "name": "Царицыно",
      "line": "Замоскворецкая линия",
      "date": "30.12.1984",
      "depth": -8.0,
      "hasConnection": true
    },
    {
      "name": "Орехово",
      "line": "Замоскворецкая линия",
      "date": "30.12.1984",
      "depth": -9.0,
      "hasConnection": false
    },
    {
      "name": "Домодедовская",
      "line": "Замоскворецкая линия",
      "date": "07.09.1985",
      "depth": -9.5,
      "hasConnection": false
    },
    {
      "name": "Красногвардеиская",
      "line": "Замоскворецкая линия",
      "date": "07.09.1985",
      "depth": -9.0,
      "hasConnection": false
    },
    {
      "name": "Алма-Атинская",
      "line": "Замоскворецкая линия",
      "date": "24.12.2012",
      "depth": -10.0,
      "hasConnection": false
    },
    {
      "name": "Пятницкое шоссе",
      "line": "Арбатско-Покровская линия",
      "date": "28.12.2012",
      "depth": -11.0,
      "hasConnection": false
    },
    {
      "name": "Митино",
      "line": "Арбатско-Покровская линия",
      "date": "26.12.2009",
      "depth": -14.0,
      "hasConnection": false
    },
    {
      "name": "Волоколамская",
      "line": "Арбатско-Покровская линия",
      "date": "26.12.2009",
      "depth": -14.0,
      "hasConnection": true
    },
    {
      "name": "Мякинино",
      "line": "Арбатско-Покровская линия",
      "date": "26.12.2009",
      "depth": 0.0,
      "hasConnection": false
    },
    {
      "name": "Строгино",
      "line": "Арбатско-Покровская линия",
      "date": "07.01.2008",
      "depth": -8.0,
      "hasConnection": false
    },
    {
      "name": "Крылатское",
      "line": "Арбатско-Покровская линия",
      "date": "31.12.1989",
      "depth": -9.5,
      "hasConnection": false
    },
    {
      "name": "Молодежная",
      "line": "Арбатско-Покровская линия",
      "date": "05.07.1965",
      "depth": -6.5,
      "hasConnection": false
    },
    {
      "name": "Кунцевская",
      "line": "Арбатско-Покровская линия",
      "date": "31.08.1965",
      "depth": 0.0,
      "hasConnection": true
    },
    {
      "name": "Славянскии бульвар",
      "line": "Арбатско-Покровская линия",
      "date": "07.09.2008",
      "depth": -8.5,
      "hasConnection": false
    },
    {
      "name": "Парк Победы",
      "line": "Арбатско-Покровская линия",
      "date": "31.01.2014",
      "depth": -73.6,
      "hasConnection": true
    },
    {
      "name": "Киевская",
      "line": "Арбатско-Покровская линия",
      "date": "14.03.1954",
      "depth": -8.7,
      "hasConnection": true
    },
    {
      "name": "Смоленская",
      "line": "Арбатско-Покровская линия",
      "date": "05.04.1953",
      "depth": -50.0,
      "hasConnection": false
    },
    {
      "name": "Арбатская",
      "line": "Арбатско-Покровская линия",
      "date": "15.05.1935",
      "depth": -8.0,
      "hasConnection": true
    },
    {
      "name": "Площадь Революции",
      "line": "Арбатско-Покровская линия",
      "date": "13.03.1938",
      "depth": -33.6,
      "hasConnection": true
    },
    {
      "name": "Курская",
      "line": "Арбатско-Покровская линия",
      "date": "01.01.1950",
      "depth": -40.0,
      "hasConnection": true
    },
    {
      "name": "Бауманская",
      "line": "Арбатско-Покровская линия",
      "date": "18.01.1944",
      "depth": -32.5,
      "hasConnection": false
    },
    {
      "name": "Электрозаводская",
      "line": "Арбатско-Покровская линия",
      "date": "31.12.2020",
      "depth": -20.0,
      "hasConnection": true
    },
    {
      "name": "Семеновская",
      "line": "Арбатско-Покровская линия",
      "date": "18.01.1944",
      "depth": -40.0,
      "hasConnection": false
    },
    {
      "name": "Партизанская",
      "line": "Арбатско-Покровская линия",
      "date": "18.01.1944",
      "depth": -9.0,
      "hasConnection": true
    },
    {
      "name": "Измаиловская",
      "line": "Арбатско-Покровская линия",
      "date": "21.10.1961",
      "depth": 0.0,
      "hasConnection": false
    },
    {
      "name": "Первомаиская",
      "line": "Арбатско-Покровская линия",
      "date": "21.10.1961",
      "depth": -7.0,
      "hasConnection": false
    },
    {
      "name": "Щелковская",
      "line": "Арбатско-Покровская линия",
      "date": "22.07.1963",
      "depth": -8.0,
      "hasConnection": false
    },
    {
      "name": "Александровскии сад",
      "line": "Филевская линия",
      "date": "15.05.1935",
      "depth": -7.0,
      "hasConnection": false
    },
    {
      "name": "Арбатская",
      "line": "Филевская линия",
      "date": "15.05.1935",
      "depth": -8.0,
      "hasConnection": true
    },
    {
      "name": "Смоленская",
      "line": "Филевская линия",
      "date": "05.04.1953",
      "depth": -50.0,
      "hasConnection": false
    },
    {
      "name": "Киевская",
      "line": "Филевская линия",
      "date": "14.03.1954",
      "depth": -8.7,
      "hasConnection": true
    },
    {
      "name": "Студенческая",
      "line": "Филевская линия",
      "date": "07.11.1958",
      "depth": 0.0,
      "hasConnection": false
    },
    {
      "name": "Кутузовская",
      "line": "Филевская линия",
      "date": "07.11.1958",
      "depth": 0.0,
      "hasConnection": true
    },
    {
      "name": "Фили",
      "line": "Филевская линия",
      "date": "07.11.1959",
      "depth": 0.0,
      "hasConnection": true
    },
    {
      "name": "Багратионовская",
      "line": "Филевская линия",
      "date": "13.10.1961",
      "depth": 0.0,
      "hasConnection": false
    },
    {
      "name": "Филевскии парк",
      "line": "Филевская линия",
      "date": "13.10.1961",
      "depth": 0.0,
      "hasConnection": false
    },
    {
      "name": "Пионерская",
      "line": "Филевская линия",
      "date": "13.10.1961",
      "depth": 0.0,
      "hasConnection": false
    },
    {
      "name": "Кунцевская",
      "line": "Филевская линия",
      "date": "31.08.1965",
      "depth": 0.0,
      "hasConnection": true
    },
    {
      "name": "Выставочная",
      "line": "Филевская линия",
      "date": "10.09.2005",
      "depth": -25.0,
      "hasConnection": true
    },
    {
      "name": "Международная",
      "line": "Филевская линия",
      "date": "30.08.2006",
      "depth": -25.0,
      "hasConnection": true
    },
    {
      "name": "Киевская",
      "line": "Кольцевая линия",
      "date": "14.03.1954",
      "depth": -8.7,
      "hasConnection": true
    },
    {
      "name": "Парк Культуры",
      "line": "Кольцевая линия",
      "date": "01.01.1950",
      "depth": -40.0,
      "hasConnection": true
    },
    {
      "name": "Октябрьская",
      "line": "Кольцевая линия",
      "date": "13.10.1962",
      "depth": -40.0,
      "hasConnection": true
    },
    {
      "name": "Добрынинская",
      "line": "Кольцевая линия",
      "date": "01.01.1950",
      "depth": -35.5,
      "hasConnection": true
    },
    {
      "name": "Павелецкая",
      "line": "Кольцевая линия",
      "date": "01.01.1950",
      "depth": -33.5,
      "hasConnection": true
    },
    {
      "name": "Таганская",
      "line": "Кольцевая линия",
      "date": "31.12.1966",
      "depth": -53.0,
      "hasConnection": true
    },
    {
      "name": "Курская",
      "line": "Кольцевая линия",
      "date": "01.01.1950",
      "depth": -40.0,
      "hasConnection": true
    },
    {
      "name": "Комсомольская",
      "line": "Кольцевая линия",
      "date": "15.05.1935",
      "depth": -8.0,
      "hasConnection": true
    },
    {
      "name": "Проспект Мира",
      "line": "Кольцевая линия",
      "date": "30.01.1952",
      "depth": -40.0,
      "hasConnection": true
    },
    {
      "name": "Новослободская",
      "line": "Кольцевая линия",
      "date": "30.01.1952",
      "depth": -40.0,
      "hasConnection": true
    },
    {
      "name": "Белорусская",
      "line": "Кольцевая линия",
      "date": "11.09.1938",
      "depth": -33.1,
      "hasConnection": true
    },
    {
      "name": "Краснопресненская",
      "line": "Кольцевая линия",
      "date": "14.03.1954",
      "depth": -35.5,
      "hasConnection": true
    },
    {
      "name": "Новоясеневская",
      "line": "Калужско-Рижская линия",
      "date": "17.01.1990",
      "depth": -7.0,
      "hasConnection": true
    },
    {
      "name": "Ясенево",
      "line": "Калужско-Рижская линия",
      "date": "17.01.1990",
      "depth": -8.0,
      "hasConnection": false
    },
    {
      "name": "Теплыи стан",
      "line": "Калужско-Рижская линия",
      "date": "06.11.1987",
      "depth": -8.0,
      "hasConnection": false
    },
    {
      "name": "Коньково",
      "line": "Калужско-Рижская линия",
      "date": "06.11.1987",
      "depth": -8.0,
      "hasConnection": false
    },
    {
      "name": "Беляево",
      "line": "Калужско-Рижская линия",
      "date": "12.08.1974",
      "depth": -12.0,
      "hasConnection": false
    },
    {
      "name": "Калужская",
      "line": "Калужско-Рижская линия",
      "date": "12.08.1974",
      "depth": -10.0,
      "hasConnection": false
    },
    {
      "name": "Новые Черемушки",
      "line": "Калужско-Рижская линия",
      "date": "13.10.1962",
      "depth": -7.0,
      "hasConnection": false
    },
    {
      "name": "Профсоюзная",
      "line": "Калужско-Рижская линия",
      "date": "13.10.1962",
      "depth": -7.0,
      "hasConnection": false
    },
    {
      "name": "Академическая",
      "line": "Калужско-Рижская линия",
      "date": "13.10.1962",
      "depth": -8.5,
      "hasConnection": false
    },
    {
      "name": "Ленинскии проспект",
      "line": "Калужско-Рижская линия",
      "date": "13.10.1962",
      "depth": -16.0,
      "hasConnection": false
    },
    {
      "name": "Шаболовская",
      "line": "Калужско-Рижская линия",
      "date": "06.11.1980",
      "depth": -46.5,
      "hasConnection": false
    },
    {
      "name": "Октябрьская",
      "line": "Калужско-Рижская линия",
      "date": "13.10.1962",
      "depth": -40.0,
      "hasConnection": true
    },
    {
      "name": "Третьяковская",
      "line": "Калужско-Рижская линия",
      "date": "03.01.1971",
      "depth": -46.0,
      "hasConnection": true
    },
    {
      "name": "Китаи-город",
      "line": "Калужско-Рижская линия",
      "date": "03.01.1971",
      "depth": -29.0,
      "hasConnection": false
    },
    {
      "name": "Тургеневская",
      "line": "Калужско-Рижская линия",
      "date": "05.01.1972",
      "depth": -49.0,
      "hasConnection": true
    },
    {
      "name": "Сухаревская",
      "line": "Калужско-Рижская линия",
      "date": "05.01.1972",
      "depth": -43.0,
      "hasConnection": false
    },
    {
      "name": "Проспект Мира",
      "line": "Калужско-Рижская линия",
      "date": "30.01.1952",
      "depth": -40.0,
      "hasConnection": true
    },
    {
      "name": "Рижская",
      "line": "Калужско-Рижская линия",
      "date": "01.05.1958",
      "depth": -46.0,
      "hasConnection": false
    },
    {
      "name": "Алексеевская",
      "line": "Калужско-Рижская линия",
      "date": "01.05.1958",
      "depth": -51.0,
      "hasConnection": false
    },
    {
      "name": "ВДНХ",
      "line": "Калужско-Рижская линия",
      "date": "01.05.1958",
      "depth": -53.5,
      "hasConnection": false
    },
    {
      "name": "Ботаническии сад",
      "line": "Калужско-Рижская линия",
      "date": "30.09.1978",
      "depth": -7.0,
      "hasConnection": false
    },
    {
      "name": "Свиблово",
      "line": "Калужско-Рижская линия",
      "date": "30.09.1978",
      "depth": -8.0,
      "hasConnection": false
    },
    {
      "name": "Бабушкинская",
      "line": "Калужско-Рижская линия",
      "date": "30.09.1978",
      "depth": -10.0,
      "hasConnection": false
    },
    {
      "name": "Медведково",
      "line": "Калужско-Рижская линия",
      "date": "30.09.1978",
      "depth": -10.0,
      "hasConnection": false
    },
    {
      "name": "Котельники",
      "line": "Таганско-Краснопресненская линия",
      "date": "21.09.2015",
      "depth": -15.0,
      "hasConnection": false
    },
    {
      "name": "Жулебино",
      "line": "Таганско-Краснопресненская линия",
      "date": "09.11.2013",
      "depth": -15.0,
      "hasConnection": false
    },
    {
      "name": "Лермонтовскии проспект",
      "line": "Таганско-Краснопресненская линия",
      "date": "09.11.2013",
      "depth": -12.0,
      "hasConnection": false
    },
    {
      "name": "Выхино",
      "line": "Таганско-Краснопресненская линия",
      "date": "31.12.1966",
      "depth": 0.0,
      "hasConnection": false
    },
    {
      "name": "Рязанскии проспект",
      "line": "Таганско-Краснопресненская линия",
      "date": "31.12.1966",
      "depth": -6.0,
      "hasConnection": false
    },
    {
      "name": "Кузьминки",
      "line": "Таганско-Краснопресненская линия",
      "date": "31.12.1966",
      "depth": -8.0,
      "hasConnection": false
    },
    {
      "name": "Текстильщики",
      "line": "Таганско-Краснопресненская линия",
      "date": "31.12.1966",
      "depth": -13.0,
      "hasConnection": true
    },
    {
      "name": "Волгоградскии проспект",
      "line": "Таганско-Краснопресненская линия",
      "date": "31.12.1966",
      "depth": -8.0,
      "hasConnection": false
    },
    {
      "name": "Пролетарская",
      "line": "Таганско-Краснопресненская линия",
      "date": "31.12.1966",
      "depth": -9.0,
      "hasConnection": true
    },
    {
      "name": "Таганская",
      "line": "Таганско-Краснопресненская линия",
      "date": "31.12.1966",
      "depth": -53.0,
      "hasConnection": true
    },
    {
      "name": "Китаи-город",
      "line": "Таганско-Краснопресненская линия",
      "date": "03.01.1971",
      "depth": -29.0,
      "hasConnection": false
    },
    {
      "name": "Кузнецкии мост",
      "line": "Таганско-Краснопресненская линия",
      "date": "17.12.1975",
      "depth": -39.5,
      "hasConnection": false
    },
    {
      "name": "Пушкинская",
      "line": "Таганско-Краснопресненская линия",
      "date": "17.12.1975",
      "depth": -51.0,
      "hasConnection": true
    },
    {
      "name": "Баррикадная",
      "line": "Таганско-Краснопресненская линия",
      "date": "30.12.1972",
      "depth": -30.0,
      "hasConnection": true
    },
    {
      "name": "Улица 1905 года",
      "line": "Таганско-Краснопресненская линия",
      "date": "30.12.1972",
      "depth": -11.0,
      "hasConnection": false
    },
    {
      "name": "Беговая",
      "line": "Таганско-Краснопресненская линия",
      "date": "30.12.1972",
      "depth": -9.0,
      "hasConnection": true
    },
    {
      "name": "Полежаевская",
      "line": "Таганско-Краснопресненская линия",
      "date": "30.12.1972",
      "depth": -10.0,
      "hasConnection": true
    },
    {
      "name": "Октябрьское Поле",
      "line": "Таганско-Краснопресненская линия",
      "date": "30.12.1972",
      "depth": -9.0,
      "hasConnection": true
    },
    {
      "name": "Щукинская",
      "line": "Таганско-Краснопресненская линия",
      "date": "30.12.1975",
      "depth": -13.0,
      "hasConnection": false
    },
    {
      "name": "Спартак",
      "line": "Таганско-Краснопресненская линия",
      "date": "27.08.2014",
      "depth": -10.0,
      "hasConnection": false
    },
    {
      "name": "Тушинская",
      "line": "Таганско-Краснопресненская линия",
      "date": "30.12.1975",
      "depth": -10.5,
      "hasConnection": true
    },
    {
      "name": "Сходненская",
      "line": "Таганско-Краснопресненская линия",
      "date": "30.12.1975",
      "depth": -6.0,
      "hasConnection": false
    },
    {
      "name": "Планерная",
      "line": "Таганско-Краснопресненская линия",
      "date": "30.12.1975",
      "depth": -6.0,
      "hasConnection": false
    },
    {
      "name": "Новокосино",
      "line": "Калининско-Солнцевская линия",
      "date": "30.08.2012",
      "depth": -9.0,
      "hasConnection": false
    },
    {
      "name": "Новогиреево",
      "line": "Калининско-Солнцевская линия",
      "date": "30.12.1979",
      "depth": -9.0,
      "hasConnection": false
    },
    {
      "name": "Перово",
      "line": "Калининско-Солнцевская линия",
      "date": "30.12.1979",
      "depth": -9.0,
      "hasConnection": false
    },
    {
      "name": "Шоссе Энтузиастов",
      "line": "Калининско-Солнцевская линия",
      "date": "30.12.1979",
      "depth": 5.0,
      "hasConnection": true
    },
    {
      "name": "Авиамоторная",
      "line": "Калининско-Солнцевская линия",
      "date": "30.12.1979",
      "depth": -53.0,
      "hasConnection": true
    },
    {
      "name": "Площадь Ильича",
      "line": "Калининско-Солнцевская линия",
      "date": "30.12.1979",
      "depth": -46.0,
      "hasConnection": true
    },
    {
      "name": "Марксистская",
      "line": "Калининско-Солнцевская линия",
      "date": "30.12.1979",
      "depth": -60.0,
      "hasConnection": true
    },
    {
      "name": "Третьяковская",
      "line": "Калининско-Солнцевская линия",
      "date": "03.01.1971",
      "depth": -46.0,
      "hasConnection": true
    },
    {
      "name": "Деловои центр",
      "line": "Калининско-Солнцевская линия",
      "date": "26.02.2018",
      "depth": -30.0,
      "hasConnection": false
    },
    {
      "name": "Парк Победы",
      "line": "Калининско-Солнцевская линия",
      "date": "31.01.2014",
      "depth": -73.6,
      "hasConnection": true
    },
    {
      "name": "Минская",
      "line": "Калининско-Солнцевская линия",
      "date": "16.03.2017",
      "depth": -15.0,
      "hasConnection": false
    },
    {
      "name": "Ломоносовскии проспект",
      "line": "Калининско-Солнцевская линия",
      "date": "16.03.2017",
      "depth": -15.0,
      "hasConnection": false
    },
    {
      "name": "Раменки",
      "line": "Калининско-Солнцевская линия",
      "date": "16.03.2017",
      "depth": -15.0,
      "hasConnection": false
    },
    {
      "name": "Мичуринскии проспект",
      "line": "Калининско-Солнцевская линия",
      "date": "30.08.2018",
      "depth": -13.0,
      "hasConnection": false
    },
    {
      "name": "Озерная",
      "line": "Калининско-Солнцевская линия",
      "date": "30.08.2018",
      "depth": -25.0,
      "hasConnection": false
    },
    {
      "name": "Говорово",
      "line": "Калининско-Солнцевская линия",
      "date": "30.08.2018",
      "depth": -14.0,
      "hasConnection": false
    },
    {
      "name": "Солнцево",
      "line": "Калининско-Солнцевская линия",
      "date": "30.08.2018",
      "depth": -13.0,
      "hasConnection": false
    },
    {
      "name": "Боровское шоссе",
      "line": "Калининско-Солнцевская линия",
      "date": "30.08.2018",
      "depth": -20.0,
      "hasConnection": false
    },
    {
      "name": "Новопеределкино",
      "line": "Калининско-Солнцевская линия",
      "date": "30.08.2018",
      "depth": -16.0,
      "hasConnection": false
    },
    {
      "name": "Рассказовка",
      "line": "Калининско-Солнцевская линия",
      "date": "30.08.2018",
      "depth": -12.0,
      "hasConnection": false
    },
    {
      "name": "Бульвар Дмитрия Донского",
      "line": "Серпуховско-Тимирязевская линия",
      "date": "26.12.2002",
      "depth": -10.0,
      "hasConnection": true
    },
    {
      "name": "Аннино",
      "line": "Серпуховско-Тимирязевская линия",
      "date": "12.12.2001",
      "depth": -8.0,
      "hasConnection": false
    },
    {
      "name": "Улица академика Янгеля",
      "line": "Серпуховско-Тимирязевская линия",
      "date": "31.08.2000",
      "depth": -8.0,
      "hasConnection": false
    },
    {
      "name": "Пражская",
      "line": "Серпуховско-Тимирязевская линия",
      "date": "06.11.1985",
      "depth": -9.5,
      "hasConnection": false
    },
    {
      "name": "Южная",
      "line": "Серпуховско-Тимирязевская линия",
      "date": "08.11.1983",
      "depth": -10.0,
      "hasConnection": false
    },
    {
      "name": "Чертановская",
      "line": "Серпуховско-Тимирязевская линия",
      "date": "08.11.1983",
      "depth": -10.5,
      "hasConnection": false
    },
    {
      "name": "Севастопольская",
      "line": "Серпуховско-Тимирязевская линия",
      "date": "08.11.1983",
      "depth": -13.0,
      "hasConnection": false
    },
    {
      "name": "Нахимовскии Проспект",
      "line": "Серпуховско-Тимирязевская линия",
      "date": "08.11.1983",
      "depth": -9.5,
      "hasConnection": false
    },
    {
      "name": "Нагорная",
      "line": "Серпуховско-Тимирязевская линия",
      "date": "08.11.1983",
      "depth": -9.0,
      "hasConnection": false
    },
    {
      "name": "Нагатинская",
      "line": "Серпуховско-Тимирязевская линия",
      "date": "08.11.1983",
      "depth": -13.5,
      "hasConnection": false
    },
    {
      "name": "Тульская",
      "line": "Серпуховско-Тимирязевская линия",
      "date": "08.11.1983",
      "depth": -9.5,
      "hasConnection": false
    },
    {
      "name": "Серпуховская",
      "line": "Серпуховско-Тимирязевская линия",
      "date": "08.11.1983",
      "depth": -43.0,
      "hasConnection": true
    },
    {
      "name": "Полянка",
      "line": "Серпуховско-Тимирязевская линия",
      "date": "23.01.1986",
      "depth": -36.5,
      "hasConnection": false
    },
    {
      "name": "Боровицкая",
      "line": "Серпуховско-Тимирязевская линия",
      "date": "23.01.1986",
      "depth": -46.5,
      "hasConnection": true
    },
    {
      "name": "Чеховская",
      "line": "Серпуховско-Тимирязевская линия",
      "date": "31.12.1987",
      "depth": -62.0,
      "hasConnection": true
    },
    {
      "name": "Цветнои бульвар",
      "line": "Серпуховско-Тимирязевская линия",
      "date": "31.12.1988",
      "depth": -50.0,
      "hasConnection": false
    },
    {
      "name": "Менделеевская",
      "line": "Серпуховско-Тимирязевская линия",
      "date": "31.12.1988",
      "depth": -48.5,
      "hasConnection": true
    },
    {
      "name": "Савеловская",
      "line": "Серпуховско-Тимирязевская линия",
      "date": "31.12.1988",
      "depth": -52.0,
      "hasConnection": true
    },
    {
      "name": "Дмитровская",
      "line": "Серпуховско-Тимирязевская линия",
      "date": "01.03.1991",
      "depth": -59.0,
      "hasConnection": true
    },
    {
      "name": "Тимирязевская",
      "line": "Серпуховско-Тимирязевская линия",
      "date": "20.11.2004",
      "depth": 6.0,
      "hasConnection": true
    },
    {
      "name": "Петровско-Разумовская",
      "line": "Серпуховско-Тимирязевская линия",
      "date": "01.03.1991",
      "depth": -61.0,
      "hasConnection": true
    },
    {
      "name": "Владыкино",
      "line": "Серпуховско-Тимирязевская линия",
      "date": "01.03.1991",
      "depth": -10.5,
      "hasConnection": true
    },
    {
      "name": "Отрадное",
      "line": "Серпуховско-Тимирязевская линия",
      "date": "01.03.1991",
      "depth": -9.0,
      "hasConnection": false
    },
    {
      "name": "Бибирево",
      "line": "Серпуховско-Тимирязевская линия",
      "date": "31.12.1992",
      "depth": -9.5,
      "hasConnection": false
    },
    {
      "name": "Алтуфьево",
      "line": "Серпуховско-Тимирязевская линия",
      "date": "15.07.1994",
      "depth": -9.0,
      "hasConnection": false
    },
    {
      "name": "Зябликово",
      "line": "Люблинско-Дмитровская линия",
      "date": "02.12.2011",
      "depth": -15.0,
      "hasConnection": true
    },
    {
      "name": "Шипиловская",
      "line": "Люблинско-Дмитровская линия",
      "date": "02.12.2011",
      "depth": -10.0,
      "hasConnection": false
    },
    {
      "name": "Борисово",
      "line": "Люблинско-Дмитровская линия",
      "date": "02.12.2011",
      "depth": -10.0,
      "hasConnection": false
    },
    {
      "name": "Марьино",
      "line": "Люблинско-Дмитровская линия",
      "date": "25.12.1996",
      "depth": -8.0,
      "hasConnection": false
    },
    {
      "name": "Братиславская",
      "line": "Люблинско-Дмитровская линия",
      "date": "25.12.1996",
      "depth": -8.0,
      "hasConnection": false
    },
    {
      "name": "Люблино",
      "line": "Люблинско-Дмитровская линия",
      "date": "25.12.1996",
      "depth": -8.0,
      "hasConnection": false
    },
    {
      "name": "Волжская",
      "line": "Люблинско-Дмитровская линия",
      "date": "28.12.1995",
      "depth": -8.0,
      "hasConnection": false
    },
    {
      "name": "Печатники",
      "line": "Люблинско-Дмитровская линия",
      "date": "28.12.1995",
      "depth": -5.0,
      "hasConnection": true
    },
    {
      "name": "Кожуховская",
      "line": "Люблинско-Дмитровская линия",
      "date": "28.12.1995",
      "depth": -12.0,
      "hasConnection": false
    },
    {
      "name": "Дубровка",
      "line": "Люблинско-Дмитровская линия",
      "date": "11.12.1999",
      "depth": -62.0,
      "hasConnection": true
    },
    {
      "name": "Крестьянская застава",
      "line": "Люблинско-Дмитровская линия",
      "date": "28.12.1995",
      "depth": -47.0,
      "hasConnection": true
    },
    {
      "name": "Римская",
      "line": "Люблинско-Дмитровская линия",
      "date": "28.12.1995",
      "depth": -54.0,
      "hasConnection": true
    },
    {
      "name": "Чкаловская",
      "line": "Люблинско-Дмитровская линия",
      "date": "28.12.1995",
      "depth": -51.0,
      "hasConnection": true
    },
    {
      "name": "Сретенскии бульвар",
      "line": "Люблинско-Дмитровская линия",
      "date": "29.12.2007",
      "depth": -60.0,
      "hasConnection": false
    },
    {
      "name": "Трубная",
      "line": "Люблинско-Дмитровская линия",
      "date": "30.08.2007",
      "depth": -60.0,
      "hasConnection": true
    },
    {
      "name": "Достоевская",
      "line": "Люблинско-Дмитровская линия",
      "date": "19.06.2010",
      "depth": -60.0,
      "hasConnection": false
    },
    {
      "name": "Марьина роща",
      "line": "Люблинско-Дмитровская линия",
      "date": "19.06.2010",
      "depth": -60.0,
      "hasConnection": false
    },
    {
      "name": "Бутырская",
      "line": "Люблинско-Дмитровская линия",
      "date": "16.09.2016",
      "depth": -60.0,
      "hasConnection": false
    },
    {
      "name": "Фонвизинская",
      "line": "Люблинско-Дмитровская линия",
      "date": "16.09.2016",
      "depth": -65.0,
      "hasConnection": false
    },
    {
      "name": "Петровско-Разумовская",
      "line": "Люблинско-Дмитровская линия",
      "date": "01.03.1991",
      "depth": -61.0,
      "hasConnection": true
    },
    {
      "name": "Окружная",
      "line": "Люблинско-Дмитровская линия",
      "date": "10.09.2016",
      "depth": 0.0,
      "hasConnection": true
    },
    {
      "name": "Верхние Лихоборы",
      "line": "Люблинско-Дмитровская линия",
      "date": "22.03.2018",
      "depth": -65.0,
      "hasConnection": false
    },
    {
      "name": "Селигерская",
      "line": "Люблинско-Дмитровская линия",
      "date": "22.03.2018",
      "depth": -20.0,
      "hasConnection": false
    },
    {
      "name": "Савеловская",
      "line": "Большая Кольцевая Линия",
      "date": "31.12.1988",
      "depth": -52.0,
      "hasConnection": true
    },
    {
      "name": "Петровскии парк",
      "line": "Большая Кольцевая Линия",
      "date": "26.02.2018",
      "depth": -25.0,
      "hasConnection": false
    },
    {
      "name": "ЦСКА",
      "line": "Большая Кольцевая Линия",
      "date": "26.02.2018",
      "depth": -28.0,
      "hasConnection": false
    },
    {
      "name": "Хорошевская",
      "line": "Большая Кольцевая Линия",
      "date": "26.02.2018",
      "depth": -21.0,
      "hasConnection": false
    },
    {
      "name": "Шелепиха",
      "line": "Большая Кольцевая Линия",
      "date": "26.02.2018",
      "depth": -18.0,
      "hasConnection": true
    },
    {
      "name": "Деловои центр",
      "line": "Большая Кольцевая Линия",
      "date": "26.02.2018",
      "depth": -30.0,
      "hasConnection": false
    },
    {
      "name": "Каховская",
      "line": "Каховская линия",
      "date": "11.08.1969",
      "depth": -8.0,
      "hasConnection": false
    },
    {
      "name": "Варшавская",
      "line": "Каховская линия",
      "date": "11.08.1969",
      "depth": -9.0,
      "hasConnection": false
    },
    {
      "name": "Каширская",
      "line": "Каховская линия",
      "date": "11.08.1969",
      "depth": -7.0,
      "hasConnection": true
    },
    {
      "name": "Битцевскии парк",
      "line": "Бутовская линия",
      "date": "27.02.2014",
      "depth": -10.0,
      "hasConnection": false
    },
    {
      "name": "Лесопарковая",
      "line": "Бутовская линия",
      "date": "27.02.2014",
      "depth": -10.0,
      "hasConnection": false
    },
    {
      "name": "Улица Старокачаловская",
      "line": "Бутовская линия",
      "date": "27.12.2003",
      "depth": -10.0,
      "hasConnection": true
    },
    {
      "name": "Улица Скобелевская",
      "line": "Бутовская линия",
      "date": "27.12.2003",
      "depth": 9.6,
      "hasConnection": false
    },
    {
      "name": "Бульвар адмирала Ушакова",
      "line": "Бутовская линия",
      "date": "27.12.2003",
      "depth": 9.6,
      "hasConnection": false
    },
    {
      "name": "Улица Горчакова",
      "line": "Бутовская линия",
      "date": "27.12.2003",
      "depth": 9.6,
      "hasConnection": false
    },
    {
      "name": "Бунинская Аллея",
      "line": "Бутовская линия",
      "date": "27.12.2003",
      "depth": 9.6,
      "hasConnection": false
    },
    {
      "name": "Окружная",
      "line": "Центральное Кольцо",
      "date": "10.09.2016",
      "depth": 0.0,
      "hasConnection": true
    },
    {
      "name": "Владыкино",
      "line": "Центральное Кольцо",
      "date": "01.03.1991",
      "depth": -10.5,
      "hasConnection": true
    },
    {
      "name": "Ботаническии Сад",
      "line": "Центральное Кольцо",
      "date": "30.09.1978",
      "depth": -7.0,
      "hasConnection": false
    },
    {
      "name": "Ростокино",
      "line": "Центральное Кольцо",
      "date": "10.09.2016",
      "depth": 0.0,
      "hasConnection": false
    },
    {
      "name": "Белокаменная",
      "line": "Центральное Кольцо",
      "date": "10.09.2016",
      "depth": 0.0,
      "hasConnection": false
    },
    {
      "name": "Бульвар Рокоссовского",
      "line": "Центральное Кольцо",
      "date": "10.09.2016",
      "depth": -8.0,
      "hasConnection": true
    },
    {
      "name": "Локомотив",
      "line": "Центральное Кольцо",
      "date": "10.09.2016",
      "depth": 0.0,
      "hasConnection": true
    },
    {
      "name": "Измаилово",
      "line": "Центральное Кольцо",
      "date": "10.09.2016",
      "depth": 5.0,
      "hasConnection": false
    },
    {
      "name": "Соколиная Гора",
      "line": "Центральное Кольцо",
      "date": "11.10.2016",
      "depth": -5.0,
      "hasConnection": false
    },
    {
      "name": "Шоссе Энтузиастов",
      "line": "Центральное Кольцо",
      "date": "30.12.1979",
      "depth": 5.0,
      "hasConnection": true
    },
    {
      "name": "Андроновка",
      "line": "Центральное Кольцо",
      "date": "10.09.2016",
      "depth": 0.0,
      "hasConnection": false
    },
    {
      "name": "Нижегородская",
      "line": "Центральное Кольцо",
      "date": "27.03.2020",
      "depth": 5.0,
      "hasConnection": true
    },
    {
      "name": "Новохохловская",
      "line": "Центральное Кольцо",
      "date": "10.09.2016",
      "depth": 0.0,
      "hasConnection": true
    },
    {
      "name": "Угрешская",
      "line": "Центральное Кольцо",
      "date": "10.09.2016",
      "depth": 0.0,
      "hasConnection": true
    },
    {
      "name": "Дубровка",
      "line": "Центральное Кольцо",
      "date": "11.12.1999",
      "depth": -62.0,
      "hasConnection": true
    },
    {
      "name": "Автозаводская",
      "line": "Центральное Кольцо",
      "date": "10.09.2016",
      "depth": -11.0,
      "hasConnection": true
    },
    {
      "name": "ЗИЛ",
      "line": "Центральное Кольцо",
      "date": "10.09.2016",
      "depth": 0.0,
      "hasConnection": false
    },
    {
      "name": "Верхние Котлы",
      "line": "Центральное Кольцо",
      "date": "10.09.2016",
      "depth": 0.0,
      "hasConnection": false
    },
    {
      "name": "Крымская",
      "line": "Центральное Кольцо",
      "date": "10.09.2016",
      "depth": -3.0,
      "hasConnection": false
    },
    {
      "name": "Площадь Гагарина",
      "line": "Центральное Кольцо",
      "date": "10.09.2016",
      "depth": -5.0,
      "hasConnection": true
    },
    {
      "name": "Лужники",
      "line": "Центральное Кольцо",
      "date": "10.09.2016",
      "depth": 5.0,
      "hasConnection": true
    },
    {
      "name": "Кутузовская",
      "line": "Центральное Кольцо",
      "date": "07.11.1958",
      "depth": 0.0,
      "hasConnection": true
    },
    {
      "name": "Деловои центр",
      "line": "Центральное Кольцо",
      "date": "26.02.2018",
      "depth": -30.0,
      "hasConnection": false
    },
    {
      "name": "Шелепиха",
      "line": "Центральное Кольцо",
      "date": "26.02.2018",
      "depth": -18.0,
      "hasConnection": true
    },
    {
      "name": "Хорошево",
      "line": "Центральное Кольцо",
      "date": "10.09.2016",
      "depth": 5.0,
      "hasConnection": false
    },
    {
      "name": "Зорге",
      "line": "Центральное Кольцо",
      "date": "04.11.2016",
      "depth": 0.0,
      "hasConnection": true
    },
    {
      "name": "Панфиловская",
      "line": "Центральное Кольцо",
      "date": "08.11.2016",
      "depth": 0.0,
      "hasConnection": true
    },
    {
      "name": "Стрешнево",
      "line": "Центральное Кольцо",
      "date": "10.09.2016",
      "depth": 0.0,
      "hasConnection": true
    },
    {
      "name": "Балтииская",
      "line": "Центральное Кольцо",
      "date": "10.09.2016",
      "depth": 0.0,
      "hasConnection": false
    },
    {
      "name": "Коптево",
      "line": "Центральное Кольцо",
      "date": "01.11.2016",
      "depth": 0.0,
      "hasConnection": false
    },
    {
      "name": "Лихоборы",
      "line": "Центральное Кольцо",
      "date": "10.09.2016",
      "depth": 0.0,
      "hasConnection": false
    },
    {
      "name": "Электрозаводская",
      "line": "Некрасовская линия",
      "date": "31.12.2020",
      "depth": -20.0,
      "hasConnection": true
    },
    {
      "name": "Лефортово",
      "line": "Некрасовская линия",
      "date": "27.03.2020",
      "hasConnection": false
    },
    {
      "name": "Авиамоторная",
      "line": "Некрасовская линия",
      "date": "30.12.1979",
      "depth": -53.0,
      "hasConnection": true
    },
    {
      "name": "Нижегородская",
      "line": "Некрасовская линия",
      "date": "27.03.2020",
      "depth": 5.0,
      "hasConnection": true
    },
    {
      "name": "Стахановская",
      "line": "Некрасовская линия",
      "date": "27.03.2020",
      "hasConnection": false
    },
    {
      "name": "Окская",
      "line": "Некрасовская линия",
      "date": "27.03.2020",
      "hasConnection": false
    },
    {
      "name": "Юго-Восточная",
      "line": "Некрасовская линия",
      "date": "27.03.2020",
      "depth": -20.0,
      "hasConnection": false
    },
    {
      "name": "Косино",
      "line": "Некрасовская линия",
      "date": "03.06.2019",
      "depth": -27.0,
      "hasConnection": true
    },
    {
      "name": "Улица Дмитриевского",
      "line": "Некрасовская линия",
      "date": "03.06.2019",
      "depth": -18.0,
      "hasConnection": false
    },
    {
      "name": "Лухмановская",
      "line": "Некрасовская линия",
      "date": "03.06.2019",
      "depth": -15.0,
      "hasConnection": false
    },
    {
      "name": "Некрасовка",
      "line": "Некрасовская линия",
      "date": "03.06.2019",
      "depth": -16.0,
      "hasConnection": false
    },
    {
      "name": "Нахабино",
      "line": "МЦД-2",
      "hasConnection": false
    },
    {
      "name": "Аникеевка",
      "line": "МЦД-2",
      "hasConnection": false
    },
    {
      "name": "Опалиха",
      "line": "МЦД-2",
      "hasConnection": false
    },
    {
      "name": "Красногорская",
      "line": "МЦД-2",
      "hasConnection": false
    },
    {
      "name": "Павшино",
      "line": "МЦД-2",
      "hasConnection": false
    },
    {
      "name": "Пенягино",
      "line": "МЦД-2",
      "hasConnection": false
    },
    {
      "name": "Волоколамская",
      "line": "МЦД-2",
      "date": "26.12.2009",
      "depth": -14.0,
      "hasConnection": true
    },
    {
      "name": "Трикотажная",
      "line": "МЦД-2",
      "hasConnection": false
    },
    {
      "name": "Тушино",
      "line": "МЦД-2",
      "hasConnection": true
    },
    {
      "name": "Щукинская",
      "line": "МЦД-2",
      "date": "30.12.1975",
      "depth": -13.0,
      "hasConnection": false
    },
    {
      "name": "Стрешнево",
      "line": "МЦД-2",
      "date": "10.09.2016",
      "depth": 0.0,
      "hasConnection": true
    },
    {
      "name": "Красныи Балтиец",
      "line": "МЦД-2",
      "hasConnection": false
    },
    {
      "name": "Гражданская",
      "line": "МЦД-2",
      "hasConnection": false
    },
    {
      "name": "Дмитровская",
      "line": "МЦД-2",
      "date": "01.03.1991",
      "depth": -59.0,
      "hasConnection": true
    },
    {
      "name": "Рижская",
      "line": "МЦД-2",
      "date": "01.05.1958",
      "depth": -46.0,
      "hasConnection": false
    },
    {
      "name": "Каланчевская",
      "line": "МЦД-2",
      "hasConnection": false
    },
    {
      "name": "Курская",
      "line": "МЦД-2",
      "date": "01.01.1950",
      "depth": -40.0,
      "hasConnection": true
    },
    {
      "name": "Москва Товарная",
      "line": "МЦД-2",
      "hasConnection": true
    },
    {
      "name": "Калитники",
      "line": "МЦД-2",
      "hasConnection": false
    },
    {
      "name": "Новохохловская",
      "line": "МЦД-2",
      "date": "10.09.2016",
      "depth": 0.0,
      "hasConnection": true
    },
    {
      "name": "Текстильщики",
      "line": "МЦД-2",
      "date": "31.12.1966",
      "depth": -13.0,
      "hasConnection": true
    },
    {
      "name": "Кубанская",
      "line": "МЦД-2",
      "hasConnection": true
    },
    {
      "name": "Депо",
      "line": "МЦД-2",
      "hasConnection": false
    },
    {
      "name": "Перерва",
      "line": "МЦД-2",
      "hasConnection": false
    },
    {
      "name": "Курьяново",
      "line": "МЦД-2",
      "hasConnection": false
    },
    {
      "name": "Москворечье",
      "line": "МЦД-2",
      "hasConnection": false
    },
    {
      "name": "Царицыно",
      "line": "МЦД-2",
      "date": "30.12.1984",
      "depth": -8.0,
      "hasConnection": true
    },
    {
      "name": "Покровская",
      "line": "МЦД-2",
      "hasConnection": false
    },
    {
      "name": "Красныи Строитель",
      "line": "МЦД-2",
      "hasConnection": false
    },
    {
      "name": "Битца",
      "line": "МЦД-2",
      "hasConnection": false
    },
    {
      "name": "Бутово",
      "line": "МЦД-2",
      "hasConnection": false
    },
    {
      "name": "Щербинка",
      "line": "МЦД-2",
      "hasConnection": false
    },
    {
      "name": "Остафьево",
      "line": "МЦД-2",
      "hasConnection": false
    },
    {
      "name": "Силикатная",
      "line": "МЦД-2",
      "hasConnection": false
    },
    {
      "name": "Подольск",
      "line": "МЦД-2",
      "hasConnection": false
    },
    {
      "name": "Одинцово",
      "line": "МЦД-1",
      "hasConnection": false
    },
    {
      "name": "Баковка",
      "line": "МЦД-1",
      "hasConnection": false
    },
    {
      "name": "Сколково",
      "line": "МЦД-1",
      "hasConnection": false
    },
    {
      "name": "Немчиновка",
      "line": "МЦД-1",
      "hasConnection": false
    },
    {
      "name": "Сетунь",
      "line": "МЦД-1",
      "hasConnection": false
    },
    {
      "name": "Рабочии Поселок",
      "line": "МЦД-1",
      "hasConnection": false
    },
    {
      "name": "Кунцево",
      "line": "МЦД-1",
      "hasConnection": true
    },
    {
      "name": "Славянскии бульвар",
      "line": "МЦД-1",
      "date": "07.09.2008",
      "depth": -8.5,
      "hasConnection": false
    },
    {
      "name": "Фили",
      "line": "МЦД-1",
      "date": "07.11.1959",
      "depth": 0.0,
      "hasConnection": true
    },
    {
      "name": "Тестовская",
      "line": "МЦД-1",
      "hasConnection": true
    },
    {
      "name": "Беговая",
      "line": "МЦД-1",
      "date": "30.12.1972",
      "depth": -9.0,
      "hasConnection": true
    },
    {
      "name": "Белорусская",
      "line": "МЦД-1",
      "date": "11.09.1938",
      "depth": -33.1,
      "hasConnection": true
    },
    {
      "name": "Савеловская",
      "line": "МЦД-1",
      "date": "31.12.1988",
      "depth": -52.0,
      "hasConnection": true
    },
    {
      "name": "Тимирязевская",
      "line": "МЦД-1",
      "date": "20.11.2004",
      "depth": 6.0,
      "hasConnection": true
    },
    {
      "name": "Окружная",
      "line": "МЦД-1",
      "date": "10.09.2016",
      "depth": 0.0,
      "hasConnection": true
    },
    {
      "name": "Дегунино",
      "line": "МЦД-1",
      "hasConnection": false
    },
    {
      "name": "Бескудниково",
      "line": "МЦД-1",
      "hasConnection": false
    },
    {
      "name": "Лианозово",
      "line": "МЦД-1",
      "hasConnection": false
    },
    {
      "name": "Марк",
      "line": "МЦД-1",
      "hasConnection": false
    },
    {
      "name": "Новодачная",
      "line": "МЦД-1",
      "hasConnection": false
    },
    {
      "name": "Долгопрудная",
      "line": "МЦД-1",
      "hasConnection": false
    },
    {
      "name": "Водники",
      "line": "МЦД-1",
      "hasConnection": false
    },
    {
      "name": "Хлебниково",
      "line": "МЦД-1",
      "hasConnection": false
    },
    {
      "name": "Шереметьевская",
      "line": "МЦД-1",
      "hasConnection": false
    },
    {
      "name": "Лобня",
      "line": "МЦД-1",
      "hasConnection": false
    }
  ]
}